{
  "manifestVersion": "3.2",
  "proxies": [
    {
      "address": "0x4B16719E73949a62E9A7306F352ec73F1B143c27",
      "txHash": "0x57966a066eebf1c276f54438fd3240a2c80b61cc315254033a25ecc4fb43ba71",
      "kind": "transparent"
    }
  ],
  "impls": {
    "027d80819c713986c58fb39581c01871f0084659c28fee2802da345704efe958": {
      "address": "0xe8AB3926D523Cf51FE1F50D22f091441A1a76e72",
      "txHash": "0xe60c716bc66f7cebe00ff095cca79d2f7e799da84476a7ad661be5e57945038d",
      "layout": {
        "solcVersion": "0.8.16",
        "storage": [
          {
            "label": "owner",
            "offset": 0,
            "slot": "0",
            "type": "t_address",
            "contract": "SchemaRegistry",
            "src": "contracts/SchemaRegistry.sol:9"
          },
          {
            "label": "schemas",
            "offset": 0,
            "slot": "1",
            "type": "t_mapping(t_address,t_mapping(t_string_memory_ptr,t_struct(Schema)7_storage))",
            "contract": "SchemaRegistry",
            "src": "contracts/SchemaRegistry.sol:15"
          },
          {
            "label": "initialized",
            "offset": 0,
            "slot": "2",
            "type": "t_bool",
            "contract": "SchemaRegistry",
            "src": "contracts/SchemaRegistry.sol:19"
          }
        ],
        "types": {
          "t_address": {
            "label": "address",
            "numberOfBytes": "20"
          },
          "t_bool": {
            "label": "bool",
            "numberOfBytes": "1"
          },
          "t_mapping(t_address,t_mapping(t_string_memory_ptr,t_struct(Schema)7_storage))": {
            "label": "mapping(address => mapping(string => struct SchemaRegistry.Schema))",
            "numberOfBytes": "32"
          },
          "t_mapping(t_string_memory_ptr,t_struct(Schema)7_storage)": {
            "label": "mapping(string => struct SchemaRegistry.Schema)",
            "numberOfBytes": "32"
          },
          "t_string_memory_ptr": {
            "label": "string",
            "numberOfBytes": "32"
          },
          "t_string_storage": {
            "label": "string",
            "numberOfBytes": "32"
          },
          "t_struct(Schema)7_storage": {
            "label": "struct SchemaRegistry.Schema",
            "members": [
              {
                "label": "schemaJson",
                "type": "t_string_storage",
                "offset": 0,
                "slot": "0"
              }
            ],
            "numberOfBytes": "32"
          }
        },
        "namespaces": {}
      }
    }
  }
}
